{
  "version": "7",
  "dialect": "sqlite",
  "entries": [
    {
      "idx": 0,
      "version": "6",
      "when": 1783002064166,
      "tag": "0000_fair_trish_tilby",
      "breakpoints": true
    },
    {
      "idx": 1,
      "version": "6",
      "when": 1783010106181,
      "tag": "0001_lame_vertigo",
      "breakpoints": true
    },
    {
      "idx": 2,
      "version": "6",
      "when": 1783512000000,
      "tag": "0002_attachment_metadata",
      "breakpoints": true
    },
    {
      "idx": 3,
      "version": "6",
      "when": 1783598400000,
      "tag": "0003_perf_and_reclaim",
      "breakpoints": true
    },
    {
      "idx": 4,
      "version": "6",
      "when": 1783684800000,
      "tag": "0004_drop_dead_columns",
      "breakpoints": true
    },
    {
      "idx": 5,
      "version": "6",
      "when": 1783771200000,
      "tag": "0005_remove_user",
      "breakpoints": true
    },
    {
      "idx": 6,
      "version": "6",
      "when": 1783857600000,
      "tag": "0006_rename_credentials",
      "breakpoints": true
    },
    {
      "idx": 7,
      "version": "6",
      "when": 1783944000000,
      "tag": "0007_rename_sync_vestiges",
      "breakpoints": true
    },
    {
      "idx": 8,
      "version": "6",
      "when": 1784030400000,
      "tag": "0008_likely_duplicates_live",
      "breakpoints": true
    }
  ]
}